mel_band_roformer/__init__.py
mel_band_roformer/attend.py
mel_band_roformer/download.py
mel_band_roformer/inference.py
mel_band_roformer/mel_band_roformer.py
mel_band_roformer/model_registry.py
mel_band_roformer/utils.py
mel_band_roformer/configs/config_vocals_mel_band_roformer.yaml
mel_band_roformer/data/melband_models.json
mel_band_roformer/data/overrides.json
melband_roformer_infer-0.1.1.dist-info/METADATA
melband_roformer_infer-0.1.1.dist-info/WHEEL
melband_roformer_infer-0.1.1.dist-info/entry_points.txt
melband_roformer_infer-0.1.1.dist-info/licenses/LICENSE
melband_roformer_infer-0.1.1.dist-info/RECORD
