Metadata-Version: 2.4
Name: melband-roformer-infer
Version: 0.1.1
Summary: Inference-only Mel-Band Roformer vocal separation toolkit
Project-URL: Homepage, https://github.com/openmirlab/melband-roformer-infer
Project-URL: Documentation, https://github.com/openmirlab/melband-roformer-infer#readme
Project-URL: Repository, https://github.com/openmirlab/melband-roformer-infer
Project-URL: Issues, https://github.com/openmirlab/melband-roformer-infer/issues
Author-email: OpenMIRLab <bernie40916@gmail.com>
License: MIT License
License-File: LICENSE
Keywords: audio,inference,pytorch,roformer,source-separation,vocals
Classifier: Development Status :: 4 - Beta
Classifier: Intended Audience :: Developers
Classifier: Intended Audience :: Science/Research
Classifier: License :: OSI Approved :: MIT License
Classifier: Programming Language :: Python :: 3
Classifier: Programming Language :: Python :: 3.10
Classifier: Programming Language :: Python :: 3.11
Classifier: Programming Language :: Python :: 3.12
Classifier: Topic :: Multimedia :: Sound/Audio :: Analysis
Classifier: Topic :: Scientific/Engineering :: Artificial Intelligence
Classifier: Typing :: Typed
Requires-Python: >=3.10
Requires-Dist: beartype>=0.14
Requires-Dist: einops>=0.6.1
Requires-Dist: librosa>=0.9
Requires-Dist: ml-collections>=0.1.1
Requires-Dist: numpy>=1.23
Requires-Dist: pyyaml>=6.0
Requires-Dist: requests>=2.31
Requires-Dist: rotary-embedding-torch>=0.3.5
Requires-Dist: soundfile>=0.12
Requires-Dist: torch>=2.0
Requires-Dist: tqdm>=4.64
Provides-Extra: dev
Requires-Dist: pytest>=7.0; extra == 'dev'
Requires-Dist: ruff>=0.5; extra == 'dev'
